openai_redis_vectorstore/__init__.py
openai_redis_vectorstore/base.py
openai_redis_vectorstore/schemas.py
openai_redis_vectorstore/settings.py
openai_redis_vectorstore/utils.py
openai_redis_vectorstore/version.py
openai_redis_vectorstore-0.2.2.dist-info/licenses/LICENSE
openai_redis_vectorstore-0.2.2.dist-info/METADATA
openai_redis_vectorstore-0.2.2.dist-info/WHEEL
openai_redis_vectorstore-0.2.2.dist-info/top_level.txt
openai_redis_vectorstore-0.2.2.dist-info/RECORD
