Metadata-Version: 2.4
Name: openai-redis-vectorstore
Version: 0.2.2
Summary: 基于RedisStack向量数据库，集成embeddings和rerank模型，支持二阶段召回，支持添加和删除等管理功能。
Author: rRR0VrFP
Maintainer: rRR0VrFP
License: Apache License, Version 2.0
Keywords: openai-redis-vectorstore
Classifier: Development Status :: 5 - Production/Stable
Classifier: Intended Audience :: Developers
Classifier: Topic :: Software Development :: Libraries :: Python Modules
Classifier: License :: OSI Approved :: Apache Software License
Classifier: Programming Language :: Python :: 3
Classifier: Programming Language :: Python :: 3 :: Only
License-File: LICENSE
Requires-Dist: PyYAML
Requires-Dist: langchain-redis
Requires-Dist: openai
Requires-Dist: openai-simple-embeddings
Requires-Dist: openai-simple-rerank
Requires-Dist: pydantic
Requires-Dist: python-environment-settings
Requires-Dist: redis
Requires-Dist: zenutils
Dynamic: author
Dynamic: classifier
Dynamic: description
Dynamic: description-content-type
Dynamic: keywords
Dynamic: license
Dynamic: license-file
Dynamic: maintainer
Dynamic: requires-dist
Dynamic: summary
